examples/__init__.py
satisfactory_ds_api/__init__.py
satisfactory_ds_api/api_client.py
satisfactory_ds_api/config.py
satisfactory_ds_api/exceptions.py
satisfactory_ds_api/models.py
satisfactory_ds_api/utils.py
satisfactory_ds_api/data/__init__.py
satisfactory_ds_api/data/advanced_game_settings.py
satisfactory_ds_api/data/minimum_privilege_level.py
satisfactory_ds_api/data/new_game_save.py
satisfactory_ds_api/data/response.py
tests/__init__.py
tests/test_api_client.py
tests/test_api_functions.py
Satisfactory_DS_API-0.1.0.dist-info/LICENSE
Satisfactory_DS_API-0.1.0.dist-info/METADATA
Satisfactory_DS_API-0.1.0.dist-info/WHEEL
Satisfactory_DS_API-0.1.0.dist-info/top_level.txt
Satisfactory_DS_API-0.1.0.dist-info/RECORD
